src/__init__.py
src/app.py
flaskapp_tchatzian-1.0.0.dist-info/METADATA
flaskapp_tchatzian-1.0.0.dist-info/WHEEL
flaskapp_tchatzian-1.0.0.dist-info/entry_points.txt
flaskapp_tchatzian-1.0.0.dist-info/top_level.txt
flaskapp_tchatzian-1.0.0.dist-info/RECORD
