Metadata-Version: 2.1
Name: flaskapp-tchatzian
Version: 1.0.0
Summary: contains some sample hello world code using Flask
Home-page: https://github.com/tchatzian/offlinemap
Author: tchatzian
Author-email: harischatzi1988@gmail.com
License: UNKNOWN
Platform: UNKNOWN
Requires-Dist: flask
